{
	"Temporary": true,
	"Owner": {
		"CompanyType": {
			"BaseObject": "ROBkJTBE",
			"ObjectType": "LaborClass",
			"Id": 0,
			"Name": "gDPLVzbIl",
			"Description": "rZvGuCcepdx"
		},
		"Emails": [
			{
				"Id": 0,
				"Email": "Myra_Tromp@yahoo.com",
				"Name": "ftFSVf",
				"Description": "UxpTBTrMsKY"
			}
		],
		"PhoneNumbers": [
			{
				"Id": 0,
				"PhoneNumber": "qGUlplvRYs",
				"Name": "isoFjKYg",
				"Description": "otJFPvS"
			}
		],
		"ObjectType": "Company",
		"Id": 0,
		"Name": "DmwdPM",
		"Description": "McSVKFklIf",
		"Address": {
			"Street": "iHgfOVWJAt",
			"StreetDetails": "BMAbtr",
			"State": {
				"BaseObject": "peoKpcq",
				"ObjectType": "PurchaseOrderStatus",
				"Id": 0,
				"Name": "paIrxMWsbkQ",
				"Description": "CCuDDtEpX"
			},
			"City": "gbwHC",
			"ZipCode": "wTsIXqRfUaF",
			"Geocode": {
				"Lat": 25,
				"Lng": 269,
				"Source": "GPSService"
			},
			"Id": 0,
			"ObjectType": "Address"
		},
		"Tags": [
			{
				"BaseObject": "FWiZrjHl",
				"AttributeId": 0,
				"ObjectType": "Attribute",
				"Id": 0,
				"Name": "JBEbCwxuKPD",
				"Description": "zPvTKmW"
			}
		],
		"AccountCode": "bxVMUU",
		"Divisions": [
			{
				"BaseObject": "utNXGJgjdrB",
				"ObjectType": "JobType",
				"Id": 0,
				"Name": "OffXlqhM",
				"Description": "nHYbxcIXdxL"
			}
		],
		"Contacts": [
			{
				"Emails": [
					{
						"Id": 0,
						"Email": "Howard17@yahoo.com",
						"Name": "kcbnqjwUI",
						"Description": "IMVMBVvlPgC"
					}
				],
				"PhoneNumbers": [
					{
						"Id": 0,
						"PhoneNumber": "xWFogwB",
						"Name": "KsfOFeiFNwF",
						"Description": "SOEYpO"
					}
				],
				"ObjectType": "Subcontractor",
				"Id": 0,
				"Name": "FmaNPSpgiZfi",
				"Description": "evCTpi",
				"Address": {
					"Street": "WXzRNWh",
					"StreetDetails": "WcfTYLb",
					"State": {
						"BaseObject": "bYWidvBA",
						"ObjectType": "JobPriority",
						"Id": 0,
						"Name": "PaJVTuboelz",
						"Description": "rWZlAcz"
					},
					"City": "ShzKCkkR",
					"ZipCode": "OnlDNd",
					"Geocode": {
						"Lat": 371,
						"Lng": 213,
						"Source": "Owner"
					},
					"Id": 0,
					"ObjectType": "Address"
				},
				"Tags": [
					{
						"BaseObject": "ZnjvGkDpdkic",
						"AttributeId": 0,
						"ObjectType": "Attribute",
						"Id": 0,
						"Name": "QSjQaXyiF",
						"Description": "zzSTbomJhYaT"
					}
				]
			}
		]
	},
	"ResourceType": {
		"Family": "Group",
		"ResourceSubtypes": [
			{
				"ObjectType": "ResourceSubtype",
				"Id": 0,
				"Name": "OXnvovfy",
				"Description": "NJiAkzXTO"
			}
		],
		"MoveVehicle": true,
		"BaseObject": "pjhGvFHuKA",
		"ObjectType": "ResourceType",
		"Id": 0,
		"Name": "lLpuNZYmUtZ",
		"Description": "cZhdJdJBLLh",
		"Tags": [
			{
				"BaseObject": "pghxLPGB",
				"AttributeId": 0,
				"ObjectType": "Attribute",
				"Id": 0,
				"Name": "TDYGgiUifib",
				"Description": "ALCNQUsmIdp"
			}
		]
	},
	"ResourceSubtype": {
		"ObjectType": "ResourceSubtype",
		"Id": 0,
		"Name": "iGmngXPjHi",
		"Description": "pPnpiIcOXX"
	},
	"UnitCost": {
		"Unit": {
			"UnitType": "Money",
			"Scalar": 531,
			"Integral": false,
			"BaseObject": "nSNjagZ",
			"ObjectType": "Unit",
			"Id": 0,
			"Name": "VGXvGFsQoWgU",
			"Description": "WFspnZcrpr"
		},
		"Cost": {
			"Unit": {
				"UnitType": "Weight",
				"Scalar": 577,
				"Integral": false,
				"BaseObject": "gjDqWocMR",
				"ObjectType": "Unit",
				"Id": 0,
				"Name": "NMLQoq",
				"Description": "zIQOyIDa"
			},
			"Quantity": 736
		},
		"Notes": "KglmRdjYvMlT"
	},
	"InCrew": false,
	"ForeColor": "ZacmEKfXMeaX",
	"BackColor": "XHdaVcCQ",
	"Location": {
		"Address": {
			"Street": "UvyOUaLjj",
			"StreetDetails": "MzSdivMSoPv",
			"State": {
				"BaseObject": "AhYDVPWAUqSi",
				"ObjectType": "License",
				"Id": 0,
				"Name": "mtrdyytEfR",
				"Description": "JhLzEB"
			},
			"City": "kTPaHK",
			"ZipCode": "hJCFlieAsUKp",
			"Geocode": {
				"Lat": 604,
				"Lng": 13,
				"Source": "GPSService"
			},
			"Id": 0,
			"ObjectType": "Address"
		},
		"Name": "NSUzCBFiH",
		"Description": "ieiyqE"
	},
	"DisplayName": "wWqarID",
	"AccountCode": "CFCjaypBt",
	"CurrentLifespan": {
		"Start": "2019-01-14T08:00:00",
		"End": "2019-01-14T08:00:00",
		"Duration": "TQjGvZDLYvu"
	},
	"Id": 0,
	"ObjectType": "Equipment",
	"Divisions": [
		{
			"BaseObject": "ivMYRvIJOIQ",
			"ObjectType": "State",
			"Id": 0,
			"Name": "bRAwRK",
			"Description": "WVmDVuLAKvRD"
		}
	],
	"Description": "OEMQDTfb",
	"Name": "rHiWDZ",
	"Tags": [
		{
			"BaseObject": "wkPwKIWx",
			"AttributeId": 0,
			"ObjectType": "Attribute",
			"Id": 0,
			"Name": "YtCWbIs",
			"Description": "rLxhTeBvKcB"
		}
	]
}