{
	"Resource": {
		"Owner": {
			"CompanyType": {
				"BaseObject": "YORMMWmCeXDy",
				"Id": 0,
				"ObjectType": "PurchaseOrderStatus",
				"Description": "TlTKdzkVfjsU",
				"Name": "MoPpqyUl",
				"Dependencies": [
					{
						"ObjectType": "iXDdWFg",
						"Ids": [
							633
						]
					}
				]
			},
			"Supplier": true,
			"Emails": [
				{
					"Email": "Columbus.Cole@hotmail.com",
					"Id": 0,
					"Description": "FDxPagzDr",
					"Name": "dlRaif"
				}
			],
			"PhoneNumbers": [
				{
					"PhoneNumber": "RyTRTfAqz",
					"Id": 0,
					"Description": "KEKhShFKG",
					"Name": "gmavxY"
				}
			],
			"HasSMSNumber": false,
			"SMSNumber": {
				"PhoneNumber": "eLstOqNf",
				"Id": 0,
				"Description": "vTycBxa",
				"Name": "VZQesJjnRWoj"
			},
			"Id": 0,
			"ObjectType": "Subcontractor",
			"Description": "Fbypeyguemof",
			"Name": "CMWIusjDa",
			"Dependencies": [
				{
					"ObjectType": "EFrxqNx",
					"Ids": [
						426
					]
				}
			],
			"CurrentLifespan": {
				"Start": "2019-01-14T08:00:00",
				"End": "2019-01-14T08:00:00",
				"Duration": "TdtodhBLIRlI"
			},
			"Start": "2019-01-14T08:00:00",
			"End": "2019-01-14T08:00:00",
			"Tags": [
				{
					"BaseObject": "AkUxqfzy",
					"AttributeId": 0,
					"Dependencies": [
						{
							"ObjectType": "CBltbxHUONIK",
							"Ids": [
								880
							]
						}
					],
					"Id": 0,
					"ObjectType": "Attribute",
					"Description": "CxaoRyHiwK",
					"Name": "eCGQOZUX"
				}
			],
			"Address": {
				"Street": "NYo",
				"StreetDetails": "NdWoyhKocEtV",
				"ZipCode": "TwdLmsWfj",
				"City": "SwPptv",
				"State": {
					"BaseObject": "NUdHImGcwN",
					"Id": 0,
					"ObjectType": "TimeEntryType",
					"Description": "vOFJBF",
					"Name": "sezPkbSnLjwj",
					"Dependencies": [
						{
							"ObjectType": "WuAsPdkOSi",
							"Ids": [
								194
							]
						}
					]
				},
				"Geocode": {
					"Lat": 862,
					"Lng": 876,
					"Source": "Action"
				},
				"Id": 0,
				"ObjectType": "Address"
			},
			"AccountCode": "eSdtEdFmDkUX",
			"Divisions": [
				{
					"BaseObject": "EVFGSg",
					"Id": 0,
					"ObjectType": "Division",
					"Description": "QwWhuxkAe",
					"Name": "xfWXyhh",
					"Dependencies": [
						{
							"ObjectType": "LSkgNat",
							"Ids": [
								897
							]
						}
					]
				}
			],
			"Contacts": [
				{
					"Emails": [
						{
							"Email": "Raymundo_Hilpert21@yahoo.com",
							"Id": 0,
							"Description": "LPqEKFm",
							"Name": "oyxniLKrRBxb"
						}
					],
					"PhoneNumbers": [
						{
							"PhoneNumber": "HZYiAXkmxrI",
							"Id": 0,
							"Description": "AcAkhTgozzW",
							"Name": "rEBKczmk"
						}
					],
					"HasSMSNumber": true,
					"SMSNumber": {
						"PhoneNumber": "lVkbTwsQ",
						"Id": 0,
						"Description": "OVLuPkp",
						"Name": "lBlSxhGdoo"
					},
					"Id": 0,
					"ObjectType": "Subcontractor",
					"Description": "MSJufI",
					"Name": "OVyXxdpgkW",
					"Dependencies": [
						{
							"ObjectType": "DhtbsdzDmEYj",
							"Ids": [
								924
							]
						}
					],
					"CurrentLifespan": {
						"Start": "2019-01-14T08:00:00",
						"End": "2019-01-14T08:00:00",
						"Duration": "MOmmQlSLcQAs"
					},
					"Start": "2019-01-14T08:00:00",
					"End": "2019-01-14T08:00:00",
					"Tags": [
						{
							"BaseObject": "UeVpHpd",
							"AttributeId": 0,
							"Dependencies": [
								{
									"ObjectType": "jptZoUeOQZc",
									"Ids": [
										633
									]
								}
							],
							"Id": 0,
							"ObjectType": "Attribute",
							"Description": "mSKRPJXRcx",
							"Name": "cvwQOtl"
						}
					],
					"Address": {
						"Street": "is",
						"StreetDetails": "LCPulAk",
						"ZipCode": "CzonpBct",
						"City": "GcArHWSuNj",
						"State": {
							"BaseObject": "YqpObsZz",
							"Id": 0,
							"ObjectType": "Minority",
							"Description": "dtPswgaLqo",
							"Name": "zpuupOx",
							"Dependencies": [
								{
									"ObjectType": "CZXZywbE",
									"Ids": [
										520
									]
								}
							]
						},
						"Geocode": {
							"Lat": 660,
							"Lng": 597,
							"Source": "Owner"
						},
						"Id": 0,
						"ObjectType": "Address"
					}
				}
			]
		},
		"ResourceType": {
			"Family": "Labor",
			"ResourceSubtypes": [
				{
					"ParentId": 0,
					"Dependencies": [
						{
							"ObjectType": "OSTzChqn",
							"Ids": [
								51
							]
						}
					],
					"Id": 0,
					"ObjectType": "ResourceSubtype",
					"Description": "xRaflRvWe",
					"Name": "kNZVzfLODKi"
				}
			],
			"MoveVehicle": false,
			"BaseObject": "xOfXDesK",
			"Id": 0,
			"ObjectType": "ResourceType",
			"Description": "HZgpsqVvzypi",
			"Name": "AgSOnMz",
			"Dependencies": [
				{
					"ObjectType": "HfVJyh",
					"Ids": [
						933
					]
				}
			],
			"ForeColor": "guPfrUhE",
			"BackColor": "OvmDLSWZXzu",
			"Tags": [
				{
					"BaseObject": "dJtAwAppWk",
					"AttributeId": 0,
					"Dependencies": [
						{
							"ObjectType": "uFugLRiFJ",
							"Ids": [
								39
							]
						}
					],
					"Id": 0,
					"ObjectType": "Attribute",
					"Description": "CsUGzG",
					"Name": "UnVJzvCLgydN"
				}
			]
		},
		"ResourceSubtype": {
			"ParentId": 0,
			"Dependencies": [
				{
					"ObjectType": "LOsBSyOIFvHV",
					"Ids": [
						824
					]
				}
			],
			"Id": 0,
			"ObjectType": "ResourceSubtype",
			"Description": "MhrlDO",
			"Name": "SlEVYI"
		},
		"Temporary": false,
		"UnitCost": {
			"Unit": {
				"UnitType": "Time",
				"Scalar": 216,
				"Integral": false,
				"BaseObject": "tvorrvQ",
				"Id": 0,
				"ObjectType": "Unit",
				"Description": "NechJk",
				"Name": "tZepSYn"
			},
			"Cost": {
				"Unit": {
					"UnitType": "Money",
					"Scalar": 267,
					"Integral": false,
					"BaseObject": "FVyYQlmX",
					"Id": 0,
					"ObjectType": "Unit",
					"Description": "zbGgLMghDil",
					"Name": "AkGYtqamPPk"
				},
				"Quantity": 956
			},
			"Notes": "qsImBM"
		},
		"DisplayName": "DuKkwsO",
		"CurrentLifespan": {
			"Start": "2019-01-14T08:00:00",
			"End": "2019-01-14T08:00:00",
			"Duration": "IgolJb"
		},
		"Start": "2019-01-14T08:00:00",
		"End": "2019-01-14T08:00:00",
		"Id": 0,
		"ObjectType": "Equipment",
		"Description": "onDVmgd",
		"Name": "uFWDaWPRKpQZ",
		"Tags": [
			{
				"BaseObject": "TlcRTdLBj",
				"AttributeId": 0,
				"Dependencies": [
					{
						"ObjectType": "CHQFgRdyfl",
						"Ids": [
							438
						]
					}
				],
				"Id": 0,
				"ObjectType": "Attribute",
				"Description": "mmGLWSd",
				"Name": "iIfbgyqiYTwJ"
			}
		],
		"Dependencies": [
			{
				"ObjectType": "SgrEsfnBeKJy",
				"Ids": [
					497
				]
			}
		],
		"Divisions": [
			{
				"BaseObject": "ZEQYwNLv",
				"Id": 0,
				"ObjectType": "DocumentType",
				"Description": "bSAYWcdSfo",
				"Name": "wCWhYx",
				"Dependencies": [
					{
						"ObjectType": "TglpTAayHjDY",
						"Ids": [
							301
						]
					}
				]
			}
		],
		"AccountCode": "pBhHdlm",
		"Location": {
			"Address": {
				"Street": "zMbqRpObE",
				"StreetDetails": "ngLrHiiPSP",
				"ZipCode": "uBKVjvbdMF",
				"City": "VyHTqopctNaB",
				"State": {
					"BaseObject": "HdyOhjWLBuT",
					"Id": 0,
					"ObjectType": "Skill",
					"Description": "apPUsLbNTZ",
					"Name": "OpPevQGwuPrn",
					"Dependencies": [
						{
							"ObjectType": "gWlOvDkK",
							"Ids": [
								209
							]
						}
					]
				},
				"Geocode": {
					"Lat": 423,
					"Lng": 90,
					"Source": "GPSService"
				},
				"Id": 0,
				"ObjectType": "Address"
			},
			"JobId": 0,
			"Description": "kwLnPyl",
			"Name": "DscKRaH"
		},
		"ForeColor": "bdaBoLNXAwfQ",
		"BackColor": "RbutxbUnQ"
	},
	"ResourceId": 0,
	"Range": {
		"Start": "2019-01-14T08:00:00",
		"End": "2019-01-14T08:00:00",
		"Duration": "bxPWoH"
	}
}