{
	"ObjectType": "TextMessage",
	"Name": "zPSwNAnp",
	"Text": "Db",
	"Sender": {
		"Id": 0,
		"PhoneNumber": "HqrmqnFX",
		"Name": "lyJBTsdHYUI",
		"Description": "hkSmxVuH"
	},
	"Sent": "2019-01-14T08:00:00",
	"Recipient": {
		"Id": 0,
		"PhoneNumber": "zeoCtAReYRNo",
		"Name": "QMDojxA",
		"Description": "nEcEndnNhzGU"
	},
	"Received": "2019-01-14T08:00:00",
	"Id": 0,
	"Description": "VvEmTTq",
	"Tags": [
		{
			"BaseObject": "mcjPYpsNmeUy",
			"AttributeId": 0,
			"New": false,
			"Dependencies": [
				{
					"ObjectType": "FNjSVwlCzXsk",
					"Ids": [
						274
					]
				}
			],
			"ObjectType": "Attribute",
			"Id": 0,
			"Name": "HKyUGisNJgA",
			"Description": "sXINmpWlQF"
		}
	],
	"Dependencies": [
		{
			"ObjectType": "uQRIVgMZw",
			"Ids": [
				869
			]
		}
	],
	"Attachments": [
		{
			"Attached": true,
			"FileLocation": "qyFKUiYkXY",
			"FullName": "aVXBBkU",
			"DocumentType": {
				"BaseObject": "YfMRiFVWGzdU",
				"ObjectType": "JobSubtype",
				"Id": 0,
				"Name": "JWSRKC",
				"Description": "ZDlJcjWzSw",
				"New": false,
				"Dependencies": [
					{
						"ObjectType": "ormFGoWHc",
						"Ids": [
							784
						]
					}
				]
			},
			"New": false,
			"Dependencies": [
				{
					"ObjectType": "GPknHmDlFf",
					"Ids": [
						132
					]
				}
			],
			"ObjectType": "Document",
			"Id": 0,
			"Name": "NWbRPKnlSGM",
			"Description": "KLvfHEroEv"
		}
	],
	"HasAttachments": false
}